CrayonLogger/__init__.py
CrayonLogger-1.0.2.dist-info/METADATA
CrayonLogger-1.0.2.dist-info/WHEEL
CrayonLogger-1.0.2.dist-info/top_level.txt
CrayonLogger-1.0.2.dist-info/RECORD
